xrootdlib/__about__.py
xrootdlib/__init__.py
xrootdlib/utility.py
xrootdlib/examples/__init__.py
xrootdlib/examples/XrdXrootdMon/__init__.py
xrootdlib/examples/XrdXrootdMon/pretty_print.py
xrootdlib/streams/__init__.py
xrootdlib/streams/XrdXrootdMon/__init__.py
xrootdlib/streams/XrdXrootdMon/fstat.py
xrootdlib/streams/XrdXrootdMon/map.py
xrootdlib/streams/XrdXrootdMon/redir.py
xrootdlib/streams/XrdXrootdMon/trace.py
xrootdlib/streams/XrdXrootdMon/utility.py
xrootdlib/structs/__init__.py
xrootdlib/structs/XrdXrootdMon/__init__.py
xrootdlib/structs/XrdXrootdMon/constants.py
xrootdlib/structs/XrdXrootdMon/fstat.py
xrootdlib/structs/XrdXrootdMon/map.py
xrootdlib/structs/XrdXrootdMon/plugin.py
xrootdlib/structs/XrdXrootdMon/redir.py
xrootdlib/structs/XrdXrootdMon/trace.py
xrootdlib-0.3.0.dist-info/METADATA
xrootdlib-0.3.0.dist-info/WHEEL
xrootdlib-0.3.0.dist-info/top_level.txt
xrootdlib-0.3.0.dist-info/zip-safe
xrootdlib-0.3.0.dist-info/RECORD
